[
  {
    "rollNo": "220819017661",
    "name": "SADEK ALI KHAN",
    "college": "TECHLAND PRIVATE INDUSTRIAL TRAINING INSTITUTE",
    "address": "KADMAGHATI, Chhatarkanali",
    "certificateNo": "231910000642358",
    "fees": 2000
  },
  {
    "rollNo": "220819016748",
    "name": "SHER ISLAM MOLLA",
    "college": "TECHLAND PRIVATE INDUSTRIAL TRAINING INSTITUTE",
    "address": "KADMAGHATI, Chhatarkanali",
    "certificateNo": "231910000644359",
    "fees": 2500
  },
  {
    "rollNo": "180819087215",
    "name": "BUDDHADEB DAS",
    "college": "Pragati Private ITI",
    "address": "UTTARPARAMORE, PO: RADHARGHAT, BHERHAMPORE, MURSHIDABAD",
    "certificateNo": "202040000498054",
    "fees": 3000
  },
  {
    "rollNo": "190821026025",
    "name": "GOUTAM PRADHAN",
    "college": "MECHEDA VIDYASAGAR PRIVATE ITI",
    "address": "Dupjora, Mecheda, Kolaghat, MEDINIPUR EAST, WEST BENGAL 721137",
    "certificateNo": "202140000952907",
    "fees": 2500
  },
  {
    "rollNo": "200809140896",
    "name": "ABDUL KALAM MANDAL",
    "college": "",
    "address": "",
    "certificateNo": "",
    "fees": 2000
  },
  {
    "rollNo": "190809178965",
    "name": "SAMSUL JAMAL MONDAL",
    "college": "",
    "address": "",
    "certificateNo": "210930007253041",
    "fees": 3000
  },
  {
    "rollNo": "220819021675",
    "name": "AMIR HOSSEN KHAN",
    "college": "",
    "address": "",
    "certificateNo": "232960000652384",
    "fees": 2000
  },
  {
    "rollNo": "220819014946",
    "name": "RAJU MANDAL",
    "college": "",
    "address": "",
    "certificateNo": "231910000001100",
    "fees": 2500
  },
  {
    "rollNo": "180927074658",
    "name": "OMAR FARUK KHAN",
    "college": "BANKURA PRIVATE ITI",
    "address": "DHALDANGA, BANKURA",
    "certificateNo": "202040001534789",
    "fees": 3000
  },
  {
    "rollNo": "190822034778",
    "name": "ANISUDDIN MOLLICK",
    "college": "BANKURA PRIVATE ITI",
    "address": "DHALDANGA, BANKURA",
    "certificateNo": "202140100418517",
    "fees": 2500
  },
  {
    "rollNo": "190840121420",
    "name": "SONELAL KISKU",
    "college": "PR10000998 - Mithila Private ITI",
    "address": "Vill.+P.O. Bastawara, P.S. Simri, Distt. Darbhanga, Bihar, Pin Code-847428",
    "certificateNo": "202147100413489",
    "fees": 2000
  },
  {
    "rollNo": "210809230907",
    "name": "ROKY PATRA",
    "college": "",
    "address": "",
    "certificateNo": "230990251003451",
    "fees": 2500
  },
  {
    "rollNo": "180819090289",
    "name": "MRINAL KANTI GHOSH",
    "college": "Pragati Private ITI",
    "address": "UTTARPARAMORE, PO: RADHARGHAT, BHERHAMPORE, MURSHIDABAD",
    "certificateNo": "202040020498107",
    "fees": 2000
  },
  {
    "rollNo": "180819001276",
    "name": "ANIMESH GHOSH",
    "college": "Pragati Private ITI",
    "address": "UTTARPARAMORE, PO: RADHARGHAT, BHERHAMPORE, MURSHIDABUR",
    "certificateNo": "202040020518209",
    "fees": 2500
  },
  {
    "rollNo": "180819001301",
    "name": "SUDIP BANDYOPADHYAY",
    "college": "Pragati Private ITI",
    "address": "UTTARPARAMORE, PO: RADHARGHAT, BHERHAMPORE, MURSHIDABUR",
    "certificateNo": "202040020519234",
    "fees": 3000
  },
  {
    "rollNo": "210809231916",
    "name": "MD TARIQUL ISLAM MALLICK",
    "college": "",
    "address": "",
    "certificateNo": "230980251015732",
    "fees": 2500
  },
  {
    "rollNo": "200809241871",
    "name": "NAJBUL MANDAL",
    "college": "",
    "address": "",
    "certificateNo": "230952002206981",
    "fees": 2000
  },
  {
    "rollNo": "210809242027",
    "name": "JAKIR HUSEN CHOWDHURY",
    "college": "",
    "address": "",
    "certificateNo": "230980252026843",
    "fees": 3000
  },
  {
    "rollNo": "180819101391",
    "name": "KISHOR KANTI GHOSH",
    "college": "Pragati Private ITI",
    "address": "UTTARPARAMORE, PO: RADHARGHAT, BHERHAMPORE, MURSHIDABUR",
    "certificateNo": "202040020509218",
    "fees": 2500
  },
  {
    "rollNo": "210809242029",
    "name": "TAHAJUL KHAN",
    "college": "",
    "address": "",
    "certificateNo": "230980251206834",
    "fees": 3000
  },
  {
    "rollNo": "210809252131",
    "name": "SADER ALI CHOWDHURY",
    "college": "",
    "address": "",
    "certificateNo": "230980251206945",
    "fees": 2500
  },
  {
    "rollNo": "190823045789",
    "name": "SAHARUL ISLAM MALLICK",
    "college": "",
    "address": "",
    "certificateNo": "212240200529628",
    "fees": 2000
  },
  {
    "rollNo": "200879406191",
    "name": "SADDAM HUSEN MANDAL",
    "college": "BANKURA PRIVATE ITI",
    "address": "DHALDANGA, BANKURA",
    "certificateNo": "202290070501248",
    "fees": 3000
  },
  {
    "rollNo": "210899016439",
    "name": "ABDUL RAHIM KHAN",
    "college": "",
    "address": "",
    "certificateNo": "232190010642471",
    "fees": 2500
  },
  {
    "rollNo": "190866092593",
    "name": "TANMAY GHOSH",
    "college": "",
    "address": "",
    "certificateNo": "210907200125905",
    "fees": 2000
  },
  {
    "rollNo": "180858724349",
    "name": "ALAUDDIN MALLICK",
    "college": "BANKURA PRIVATE ITI",
    "address": "DHALDANGA, BANKURA",
    "certificateNo": "201940047614815",
    "fees": 2500
  },
  {
    "rollNo": "200823458648",
    "name": "BABOR SHAIKH",
    "college": "",
    "address": "",
    "certificateNo": "22940091662037",
    "fees": 2000
  },
  {
    "rollNo": "200819760215",
    "name": "BABLU KHAN",
    "college": "",
    "address": "",
    "certificateNo": "22934000500651",
    "fees": 3000
  },
  {
    "rollNo": "230819014946",
    "name": "HAYDAR ALI KHAN",
    "college": "",
    "address": "",
    "certificateNo": "241910000001100",
    "fees": 2500
  },
  {
    "rollNo": "180819960784",
    "name": "SUBRATA DAS",
    "college": "MECHEDA VIDYASAGAR PRIVATE ITI",
    "address": "Dupjora, Mecheda, Kolaghat, MEDINIPUR EAST",
    "certificateNo": "202070106820856",
    "fees": 3000
  },
  {
    "rollNo": "180819961807",
    "name": "KARTIK BERA",
    "college": "MECHEDA VIDYASAGAR PRIVATE ITI",
    "address": "Dupjora, Mecheda, Kolaghat, MEDINIPUR EAST",
    "certificateNo": "202070106820879",
    "fees": 2500
  },
  {
    "rollNo": "210899016462",
    "name": "MAJHARUL ISLAM KHAN",
    "college": "",
    "address": "",
    "certificateNo": "232190010642490",
    "fees": 2000
  },
  {
    "rollNo": "210899016454",
    "name": "SAIFUL HOSSAIN KHAN",
    "college": "",
    "address": "",
    "certificateNo": "232190010642472",
    "fees": 2500
  },
  {
    "rollNo": "220899018742",
    "name": "SENAUL BHUINYA",
    "college": "",
    "address": "",
    "certificateNo": "242390010722423",
    "fees": 3000
  },
  {
    "rollNo": "220899018746",
    "name": "MAKDUM HOSEN MALLICK",
    "college": "",
    "address": "",
    "certificateNo": "242390010722429",
    "fees": 2000
  },
  {
    "rollNo": "201940000417406",
    "name": "JALIMUL HAQUE SARDAR",
    "college": "BANKURA PRIVATE ITI",
    "address": "DHALDANGA, BANKURA",
    "certificateNo": "201940000417406",
    "fees": 2500
  },
  {
    "rollNo": "201940000419803",
    "name": "SABIR SAHA BHANGI",
    "college": "TECHLAND PRIVATE INDUSTRIAL INSTITUTE",
    "address": "KADMAGHATI, Chhatarkanali",
    "certificateNo": "201940000419803",
    "fees": 3000
  },
  {
    "rollNo": "201940000467606",
    "name": "KALYAN PRASAD MANDAL",
    "college": "BANKURA PRIVATE ITI",
    "address": "SUKANTAPALLY, SATIGHAT, BYPASS ROAD, BANKURA",
    "certificateNo": "201940000467606",
    "fees": 2000
  },
  {
    "rollNo": "201940000417305",
    "name": "ABDUL RAJJAK KHAN",
    "college": "BANKURA PRIVATE ITI",
    "address": "DHALDANGA, BANKURA",
    "certificateNo": "201940000417305",
    "fees": 2500
  }
]